[{"id":"1406010006","name":"Domo"},{"id":"1406010015","name":"Iv Koto Setingkai"},{"id":"1406010017","name":"Kuntu"},{"id":"1406010042","name":"Kuntu Darussalam"},{"id":"1406010019","name":"Lipat Kain"},{"id":"1406010041","name":"Lipat Kain Selatan"},{"id":"1406010040","name":"Lipat Kain Utara"},{"id":"1406010014","name":"Muara Selaya"},{"id":"1406010016","name":"Padang Sawah"},{"id":"1406010020","name":"Sungai Geringging"},{"id":"1406010046","name":"Sungai Harapan"},{"id":"1406010044","name":"Sungai Liti"},{"id":"1406010021","name":"Sungai Paku"},{"id":"1406010035","name":"Sungai Raja"},{"id":"1406010034","name":"Sungai Rambai"},{"id":"1406010037","name":"Sungai Sarik"},{"id":"1406010036","name":"Tanjung Harapan"},{"id":"1406010043","name":"Tanjung Mas"},{"id":"1406010018","name":"Teluk Paman"},{"id":"1406010045","name":"Teluk Paman Timur"}]