[{"id":"1602140017","name":"Bandar Jaya"},{"id":"1602140005","name":"Banyu Biru"},{"id":"1602140002","name":"Bukit Batu"},{"id":"1602140010","name":"Jadi Mulya"},{"id":"1602140013","name":"Kerta Mukti"},{"id":"1602140019","name":"Marga Tani"},{"id":"1602140012","name":"Mukti Jaya"},{"id":"1602140014","name":"Negeri Sakti"},{"id":"1602140008","name":"Nusa Karta"},{"id":"1602140016","name":"Nusantara"},{"id":"1602140015","name":"Pangkalan Damai"},{"id":"1602140006","name":"Pangkalan Sakti"},{"id":"1602140007","name":"Rantau Karya"},{"id":"1602140003","name":"Rengas Abang"},{"id":"1602140004","name":"Simpang Heran"},{"id":"1602140009","name":"Sri Jaya Baru"},{"id":"1602140011","name":"Suka Mulya"},{"id":"1602140001","name":"Sungai Batang"},{"id":"1602140018","name":"Tirta Mulya"}]