[{"id":"1604051018","name":"Air Lingkar"},{"id":"1604051020","name":"Bandung Agung"},{"id":"1604051015","name":"Batu Rusa"},{"id":"1604051013","name":"Danau"},{"id":"1604051008","name":"Gemidar Ilir"},{"id":"1604051007","name":"Gemidar Ulu"},{"id":"1604051016","name":"Karang Agung"},{"id":"1604051001","name":"Kedaton"},{"id":"1604051012","name":"Kupang"},{"id":"1604051019","name":"Lesung Batu"},{"id":"1604051006","name":"Merindu"},{"id":"1604051004","name":"Muara Dua"},{"id":"1604051011","name":"Padang Pagun"},{"id":"1604051003","name":"Pagar Agung"},{"id":"1604051010","name":"Pagar Alam"},{"id":"1604051005","name":"Penantian"},{"id":"1604051009","name":"Rimba Sujud"},{"id":"1604051017","name":"Sawah Darat"},{"id":"1604051014","name":"Siring Agung"},{"id":"1604051002","name":"Tanjung Agung"}]