[{"id":"1606041001","name":"Danau Cala"},{"id":"1606041013","name":"Epil"},{"id":"1606041011","name":"Lais"},{"id":"1606041010","name":"Petaling"},{"id":"1606041007","name":"Purwosari"},{"id":"1606041002","name":"Rantau Keroya"},{"id":"1606041004","name":"Tanjung Agung Barat"},{"id":"1606041014","name":"Tanjung Agung Selatan"},{"id":"1606041005","name":"Tanjung Agung Timur"},{"id":"1606041006","name":"Tanjung Agung Utara"},{"id":"1606041012","name":"Teluk"},{"id":"1606041003","name":"Teluk Kijing I"},{"id":"1606041009","name":"Teluk Kijing Ii"},{"id":"1606041008","name":"Teluk Kijing Iii"}]