[{"id":"1609031005","name":"Bangun Harjo"},{"id":"1609031024","name":"Banyumas Asri"},{"id":"1609031006","name":"Karang Tengah"},{"id":"1609031022","name":"Kedu"},{"id":"1609031023","name":"Kedung Rejo"},{"id":"1609031020","name":"Kumpul Rejo"},{"id":"1609031002","name":"Limansari"},{"id":"1609031021","name":"Metro Rejo"},{"id":"1609031013","name":"Pengandonan"},{"id":"1609031015","name":"Rejodadi"},{"id":"1609031017","name":"Rowodadi"},{"id":"1609031007","name":"Sri Katon"},{"id":"1609031010","name":"Suka Maju"},{"id":"1609031018","name":"Sukodadi"},{"id":"1609031011","name":"Sukoharjo"},{"id":"1609031009","name":"Sumber Asri"},{"id":"1609031003","name":"Sumber Harjo"},{"id":"1609031004","name":"Sumber Mulyo"},{"id":"1609031019","name":"Sumedang Sari"},{"id":"1609031014","name":"Tambak Boyo"},{"id":"1609031001","name":"Tanjung Mas"},{"id":"1609031008","name":"Tanjung Sari"},{"id":"1609031012","name":"Tekorejo"}]