[{"id":"1610051005","name":"Cahaya Marga"},{"id":"1610051010","name":"Harimau Tandang"},{"id":"1610051007","name":"Kapuk"},{"id":"1610051013","name":"Lebak Pering"},{"id":"1610051001","name":"Maju Jaya"},{"id":"1610051006","name":"Mayapati"},{"id":"1610051002","name":"Naikan Tembakang"},{"id":"1610051003","name":"Pematang Bangsal"},{"id":"1610051015","name":"Pematang Bungur"},{"id":"1610051008","name":"Segayam"},{"id":"1610051011","name":"Sungai Keli"},{"id":"1610051004","name":"Sungai Lebung"},{"id":"1610051012","name":"Sungai Lebung Ulu"},{"id":"1610051014","name":"Sungai Ondok"},{"id":"1610051009","name":"Ulak Aur Standing"}]