[{"id":"1610062011","name":"Arisan Gading"},{"id":"1610062006","name":"Beti"},{"id":"1610062002","name":"Mandi  Angin"},{"id":"1610062009","name":"Meranjat I"},{"id":"1610062008","name":"Meranjat Ii"},{"id":"1610062012","name":"Meranjat Iii"},{"id":"1610062007","name":"Meranjat Ilir"},{"id":"1610062003","name":"Sukaraja Baru"},{"id":"1610062004","name":"Sukaraja Lama"},{"id":"1610062001","name":"Tanjung Dayang Selatan"},{"id":"1610062014","name":"Tanjung Dayang Utara"},{"id":"1610062005","name":"Tanjung Lubuk"},{"id":"1610062010","name":"Tebing Gerinting Selatan"},{"id":"1610062013","name":"Tebing Gerinting Utara"}]