[{"id":"1808031007","name":"Agung Dalem"},{"id":"1808031010","name":"Agung Jaya"},{"id":"1808031003","name":"Bujuk Agung"},{"id":"1808031002","name":"Catur Karya Buana Jaya"},{"id":"1808031012","name":"Mekar Jaya"},{"id":"1808031005","name":"Penawar Jaya"},{"id":"1808031011","name":"Penawar Rejo"},{"id":"1808031006","name":"Purwa Jaya"},{"id":"1808031001","name":"Ringin Sari"},{"id":"1808031004","name":"Sukamaju"},{"id":"1808031008","name":"Sumber Makmur"},{"id":"1808031009","name":"Tri Tunggal Jaya"}]