[{"id":"2104010004","name":"Bakong"},{"id":"2104010014","name":"Busung Panjang"},{"id":"2104010007","name":"Jagoh"},{"id":"2104010003","name":"Kuala Raya"},{"id":"2104010011","name":"Langkap"},{"id":"2104010001","name":"Marok Tua"},{"id":"2104010005","name":"Posek"},{"id":"2104010009","name":"Raya"},{"id":"2104010013","name":"Suak Buaya"},{"id":"2104010002","name":"Sungai Buluh"},{"id":"2104010006","name":"Sungai Harapan"},{"id":"2104010008","name":"Sungai Raya"},{"id":"2104010010","name":"Tanjung Irat"},{"id":"2104010012","name":"Tinjul"}]