[{"id":"3201100006","name":"Banjar Sari"},{"id":"3201100007","name":"Banjar Wangi"},{"id":"3201100010","name":"Banjar Waru"},{"id":"3201100012","name":"Bendungan"},{"id":"3201100008","name":"Bitung Sari"},{"id":"3201100004","name":"Bojong Murni"},{"id":"3201100011","name":"Ciawi"},{"id":"3201100003","name":"Cibedug"},{"id":"3201100001","name":"Cileungsi"},{"id":"3201100002","name":"Citapen"},{"id":"3201100005","name":"Jambu Luwuk"},{"id":"3201100013","name":"Pandansari"},{"id":"3201100009","name":"Teluk Pinang"}]