[{"id":"3210040012","name":"Argasari"},{"id":"3210040006","name":"Campaga"},{"id":"3210040002","name":"Cibeureum"},{"id":"3210040005","name":"Cicanir"},{"id":"3210040003","name":"Cikeusal"},{"id":"3210040014","name":"Ganeas"},{"id":"3210040013","name":"Gunungmanik"},{"id":"3210040004","name":"Jatipamor"},{"id":"3210040016","name":"Kertarahayu"},{"id":"3210040007","name":"Lampuyang"},{"id":"3210040001","name":"Margamukti"},{"id":"3210040017","name":"Mekarhurip"},{"id":"3210040008","name":"Mekarraharja"},{"id":"3210040011","name":"Salado"},{"id":"3210040015","name":"Sukaperna"},{"id":"3210040009","name":"Talagakulon"},{"id":"3210040010","name":"Talagawetan"}]