[{"id":"3306150019","name":"Banyuasin Kembaran"},{"id":"3306150009","name":"Banyuasin Separe"},{"id":"3306150010","name":"Guyangan"},{"id":"3306150013","name":"Jetis"},{"id":"3306150007","name":"Kali Glagah"},{"id":"3306150004","name":"Kalikalong"},{"id":"3306150001","name":"Kalinongko"},{"id":"3306150011","name":"Kalisemo"},{"id":"3306150003","name":"Karangrejo"},{"id":"3306150016","name":"Kebongunung"},{"id":"3306150015","name":"Kedungpoh"},{"id":"3306150018","name":"Kemejing"},{"id":"3306150012","name":"Loano"},{"id":"3306150014","name":"Maron"},{"id":"3306150017","name":"Mudalrejo"},{"id":"3306150021","name":"Ngargosari"},{"id":"3306150005","name":"Rimun"},{"id":"3306150020","name":"Sedayu"},{"id":"3306150006","name":"Tepansari"},{"id":"3306150008","name":"Tridadi"},{"id":"3306150002","name":"Trirejo"}]