[{"id":"3310190005","name":"Borongan"},{"id":"3310190001","name":"Glagah Wangi"},{"id":"3310190016","name":"Janti"},{"id":"3310190007","name":"Jimus"},{"id":"3310190002","name":"Kapungan"},{"id":"3310190010","name":"Karanglo"},{"id":"3310190003","name":"Kauman"},{"id":"3310190015","name":"Kebonharjo"},{"id":"3310190013","name":"Keprabon"},{"id":"3310190014","name":"Kranggan"},{"id":"3310190006","name":"Nganjat"},{"id":"3310190004","name":"Ngaran"},{"id":"3310190009","name":"Polan"},{"id":"3310190011","name":"Ponggok"},{"id":"3310190018","name":"Sidoharjo"},{"id":"3310190017","name":"Sidowayah"},{"id":"3310190008","name":"Turus"},{"id":"3310190012","name":"Wangen"}]