[{"id":"3315180016","name":"Cangkring"},{"id":"3315180015","name":"Curug"},{"id":"3315180017","name":"Gaji"},{"id":"3315180007","name":"Gebangan"},{"id":"3315180012","name":"Karangpasar"},{"id":"3315180001","name":"Kebonagung"},{"id":"3315180013","name":"Kedungwungu"},{"id":"3315180008","name":"Kejawan"},{"id":"3315180006","name":"Mangunsari"},{"id":"3315180003","name":"Medani"},{"id":"3315180014","name":"Pepe"},{"id":"3315180004","name":"Sukorejo"},{"id":"3315180011","name":"Tajemsari"},{"id":"3315180005","name":"Tanggirejo"},{"id":"3315180010","name":"Tegowanu Kulon"},{"id":"3315180009","name":"Tegowanu Wetan"},{"id":"3315180002","name":"Tlogorejo"},{"id":"3315180018","name":"Tunjungharjo"}]