[{"id":"3320040016","name":"Bandung"},{"id":"3320040011","name":"Buaran"},{"id":"3320040017","name":"Bungu"},{"id":"3320040014","name":"Datar"},{"id":"3320040010","name":"Jebol"},{"id":"3320040005","name":"Kuanyar"},{"id":"3320040001","name":"Mayong Kidul"},{"id":"3320040002","name":"Mayong Lor"},{"id":"3320040012","name":"Ngroto"},{"id":"3320040018","name":"Pancur"},{"id":"3320040004","name":"Paren"},{"id":"3320040006","name":"Pelang"},{"id":"3320040008","name":"Pelemkerep"},{"id":"3320040015","name":"Pule"},{"id":"3320040013","name":"Rajekwesi"},{"id":"3320040007","name":"Sengonbugel"},{"id":"3320040009","name":"Singorojo"},{"id":"3320040003","name":"Tigajuru"}]