[{"id":"3374130010","name":"Bangunharjo"},{"id":"3374130004","name":"Brumbungan"},{"id":"3374130006","name":"Gabahan"},{"id":"3374130003","name":"Jagalan"},{"id":"3374130002","name":"Karangkidul"},{"id":"3374130009","name":"Kauman"},{"id":"3374130011","name":"Kembangsari"},{"id":"3374130007","name":"Kranggan"},{"id":"3374130005","name":"Miroto"},{"id":"3374130012","name":"Pandansari"},{"id":"3374130001","name":"Pekunden"},{"id":"3374130014","name":"Pendrikan Kidul"},{"id":"3374130015","name":"Pendrikan Lor"},{"id":"3374130008","name":"Purwodinatan"},{"id":"3374130013","name":"Sekayu"}]