[{"id":"3507140002","name":"Bulupitu"},{"id":"3507140012","name":"Ganjaran"},{"id":"3507140005","name":"Gondanglegi Kulon"},{"id":"3507140006","name":"Gondanglegi Wetan"},{"id":"3507140011","name":"Ketawang"},{"id":"3507140004","name":"Panggungrejo"},{"id":"3507140008","name":"Putat Kidul"},{"id":"3507140009","name":"Putat Lor"},{"id":"3507140013","name":"Putukrejo"},{"id":"3507140007","name":"Sepanjang"},{"id":"3507140001","name":"Sukorejo"},{"id":"3507140003","name":"Sukosari"},{"id":"3507140014","name":"Sumberjaya"},{"id":"3507140010","name":"Urek Urek"}]