[{"id":"3507280015","name":"Ardimulyo"},{"id":"3507280003","name":"Banjararum"},{"id":"3507280007","name":"Baturetno"},{"id":"3507280014","name":"Candirenggo"},{"id":"3507280005","name":"Dengkol"},{"id":"3507280013","name":"Gunungrejo"},{"id":"3507280012","name":"Klampok"},{"id":"3507280001","name":"Langlang"},{"id":"3507280009","name":"Losari"},{"id":"3507280010","name":"Pagentan"},{"id":"3507280011","name":"Purwoasri"},{"id":"3507280016","name":"Randuagung"},{"id":"3507280008","name":"Tamanharjo"},{"id":"3507280017","name":"Toyomarto"},{"id":"3507280002","name":"Tunjungtirto"},{"id":"3507280004","name":"Watugede"},{"id":"3507280006","name":"Wonorejo"}]