[{"id":"3521080008","name":"Brangol"},{"id":"3521080001","name":"Campur Asri"},{"id":"3521080002","name":"Danguk"},{"id":"3521080007","name":"Dungmiri"},{"id":"3521080003","name":"Gempol"},{"id":"3521080010","name":"Jatipuro"},{"id":"3521080013","name":"Karangjati"},{"id":"3521080014","name":"Legundi"},{"id":"3521080017","name":"Ploso Lor"},{"id":"3521080011","name":"Puhti"},{"id":"3521080015","name":"Rejomulyo"},{"id":"3521080016","name":"Rejuno"},{"id":"3521080004","name":"Ringin Anom"},{"id":"3521080012","name":"Sawo"},{"id":"3521080005","name":"Sembung"},{"id":"3521080009","name":"Sidokerto"},{"id":"3521080006","name":"Sidorejo"}]