[{"id":"3524250010","name":"Banjarwati"},{"id":"3524250001","name":"Blimbing"},{"id":"3524250009","name":"Drajat"},{"id":"3524250002","name":"Kandangsemangkon"},{"id":"3524250011","name":"Kemantren"},{"id":"3524250008","name":"Kranji"},{"id":"3524250003","name":"Paciran"},{"id":"3524250014","name":"Paloh"},{"id":"3524250005","name":"Sendangagung"},{"id":"3524250006","name":"Sendangduwur"},{"id":"3524250012","name":"Sidokelar"},{"id":"3524250016","name":"Sidokumpul"},{"id":"3524250004","name":"Sumurgayam"},{"id":"3524250013","name":"Tlogosadang"},{"id":"3524250007","name":"Tunggul"},{"id":"3524250017","name":"Warulor"},{"id":"3524250015","name":"Weru"}]