[{"id":"5320040009","name":"Delo"},{"id":"5320040003","name":"Depe"},{"id":"5320040016","name":"Jadu"},{"id":"5320040015","name":"Ledeana"},{"id":"5320040017","name":"Ledekepaka"},{"id":"5320040013","name":"Mebba"},{"id":"5320040010","name":"Menia"},{"id":"5320040008","name":"Nadawawi"},{"id":"5320040018","name":"Raedewa"},{"id":"5320040007","name":"Raekore"},{"id":"5320040011","name":"Raeloro"},{"id":"5320040014","name":"Raemadia"},{"id":"5320040005","name":"Raemude"},{"id":"5320040002","name":"Raenalulu"},{"id":"5320040006","name":"Raenyale"},{"id":"5320040012","name":"Roboaba"},{"id":"5320040001","name":"Teriwu"},{"id":"5320040004","name":"Titinalede"}]