[{"id":"6301090008","name":"Bukit Mulia"},{"id":"6301090010","name":"Kebun Raya"},{"id":"6301090006","name":"Kintap"},{"id":"6301090005","name":"Kintap Kecil"},{"id":"6301090003","name":"Kintapura"},{"id":"6301090011","name":"Mekar Sari"},{"id":"6301090007","name":"Muara Kintap"},{"id":"6301090001","name":"Pandansari"},{"id":"6301090004","name":"Pasir Putih"},{"id":"6301090014","name":"Riam Adungan"},{"id":"6301090002","name":"Salaman"},{"id":"6301090012","name":"Sebamban Baru"},{"id":"6301090009","name":"Sumber Jaya"},{"id":"6301090013","name":"Sungai Cuka"}]