[{"id":"7403101004","name":"B E S U"},{"id":"7403101013","name":"Diolo"},{"id":"7403101014","name":"L A O S U"},{"id":"7403101015","name":"Lalonggaluku"},{"id":"7403101028","name":"Lalonggaluku Timur"},{"id":"7403101027","name":"Laosu Jaya"},{"id":"7403101001","name":"Mendikonu"},{"id":"7403101008","name":"P A K U"},{"id":"7403101005","name":"Paku Jaya"},{"id":"7403101011","name":"Pebunooha"},{"id":"7403101010","name":"Pebunooha Dalam"},{"id":"7403101029","name":"Porara"},{"id":"7403101009","name":"Puuruy"},{"id":"7403101026","name":"Rambu Kongga"},{"id":"7403101012","name":"Rumbia"},{"id":"7403101007","name":"Sampara\/morosi"},{"id":"7403101003","name":"Tanggobu"},{"id":"7403101006","name":"Tondowatu"},{"id":"7403101002","name":"Wonua Morini"}]