[{"id":"9415050010","name":"Akamar"},{"id":"9415050002","name":"Amborep"},{"id":"9415050005","name":"Ayam \/ Akat"},{"id":"9415050014","name":"Bayiw Pinam"},{"id":"9415050007","name":"Beco"},{"id":"9415050009","name":"Betkuar"},{"id":"9415050011","name":"Birak"},{"id":"9415050015","name":"Cumnew"},{"id":"9415050016","name":"Juwes Doar"},{"id":"9415050012","name":"Katew"},{"id":"9415050006","name":"Manep"},{"id":"9415050004","name":"Pau"},{"id":"9415050001","name":"Sesakam"},{"id":"9415050013","name":"Wau Cesaw"},{"id":"9415050003","name":"Yetsy"},{"id":"9415050008","name":"Yuni"}]