[{"id":"9416010049","name":"Air Garam"},{"id":"9416010027","name":"Anjelma"},{"id":"9416010048","name":"Eroma"},{"id":"9416010043","name":"Esalien"},{"id":"9416010054","name":"Hesmat"},{"id":"9416010029","name":"Hihundes"},{"id":"9416010052","name":"Huguma"},{"id":"9416010051","name":"Huken"},{"id":"9416010025","name":"Ibiroma"},{"id":"9416010038","name":"Kilise"},{"id":"9416010039","name":"Kima"},{"id":"9416010045","name":"Lotia\/huglot"},{"id":"9416010040","name":"Luhulema"},{"id":"9416010028","name":"Obolma"},{"id":"9416010053","name":"Parela"},{"id":"9416010046","name":"Pusuaga"},{"id":"9416010047","name":"Soroh"},{"id":"9416010044","name":"Tukuarek"},{"id":"9416010026","name":"Wanem"},{"id":"9416010042","name":"Wulik Punua"},{"id":"9416010050","name":"Wuluagaima"},{"id":"9416010041","name":"Yagarelo"}]