[{"id":"9431010002","name":"Anduang"},{"id":"9431010010","name":"Baliklabur"},{"id":"9431010004","name":"Boroges"},{"id":"9431010015","name":"Dokle"},{"id":"9431010006","name":"Gimbis"},{"id":"9431010007","name":"Guawage"},{"id":"9431010009","name":"Keniwa"},{"id":"9431010005","name":"Kobakma"},{"id":"9431010008","name":"Luarima"},{"id":"9431010014","name":"Moga"},{"id":"9431010001","name":"Ninugagas"},{"id":"9431010012","name":"Samabegulik"},{"id":"9431010003","name":"Seralema"},{"id":"9431010013","name":"Wiyugobak"},{"id":"9431010011","name":"Yagalim"}]