[{"id":"1409020","name":" Bagan Sinembah"},{"id":"1409040","name":" Bangko"},{"id":"1409051","name":" Bangko Pusako"},{"id":"1409042","name":" Batu Hampar"},{"id":"1409030","name":" Kubu"},{"id":"1409032","name":" Kubu Babussalam"},{"id":"1409031","name":" Pasir Limau Kapas"},{"id":"1409043","name":" Pekaitan"},{"id":"1409011","name":" Pujud"},{"id":"1409013","name":" Rantau Kopar"},{"id":"1409050","name":" Rimba Melintang"},{"id":"1409021","name":" Simpang Kanan"},{"id":"1409041","name":" Sinaboi"},{"id":"1409010","name":" Tanah Putih"},{"id":"1409012","name":" Tanah Putih Tanjung Melawan"}]