[{"id":"3329090","name":" Banjarharjo"},{"id":"3329020","name":" Bantarkawung"},{"id":"3329170","name":" Brebes"},{"id":"3329130","name":" Bulakamba"},{"id":"3329030","name":" Bumiayu"},{"id":"3329160","name":" Jatibarang"},{"id":"3329120","name":" Kersana"},{"id":"3329080","name":" Ketanggungan"},{"id":"3329070","name":" Larangan"},{"id":"3329100","name":" Losari"},{"id":"3329040","name":" Paguyangan"},{"id":"3329010","name":" Salem"},{"id":"3329050","name":" Sirampog"},{"id":"3329150","name":" Songgom"},{"id":"3329110","name":" Tanjung"},{"id":"3329060","name":" Tonjong"},{"id":"3329140","name":" Wanasari"}]