[{"id":"6107070","name":" Ambalau"},{"id":"6107180","name":" Binjai Hulu"},{"id":"6107150","name":" Dedai"},{"id":"6107160","name":" Kayan Hilir"},{"id":"6107080","name":" Kayan Hulu"},{"id":"6107170","name":" Kelam Permai"},{"id":"6107190","name":" Ketungau Hilir"},{"id":"6107210","name":" Ketungau Hulu"},{"id":"6107200","name":" Ketungau Tengah"},{"id":"6107110","name":" Sepauk"},{"id":"6107060","name":" Serawai"},{"id":"6107140","name":" Sintang"},{"id":"6107130","name":" Sungai Tebelian"},{"id":"6107120","name":" Tempunak"}]